{
    "0": {
        "": "0",
        "Severity": "3",
        "year": "2016",
        "lat": "39.865147",
        "lon": "-84.058723",
        "Temperature": "36.9",
        "Pressure": "29.68",
        "Visibility": "10",
        "wheather": "light rain",
        "Day_night": "night",
        "WindSpeed": "3.5"
    },
    "1": {
        "": "1",
        "Severity": "2",
        "year": "2016",
        "lat": "39.92805900000001",
        "lon": "-82.831184",
        "Temperature": "37.9",
        "Pressure": "29.65",
        "Visibility": "10",
        "wheather": "light rain",
        "Day_night": "night",
        "WindSpeed": "4.6"
    },
    "2": {
        "": "2",
        "Severity": "4",
        "year": "2016",
        "lat": "39.063148",
        "lon": "-84.032608",
        "Temperature": "36.0",
        "Pressure": "29.67",
        "Visibility": "10",
        "wheather": "overcast",
        "Day_night": "night",
        "WindSpeed": "3.5"
    },
    "3": {
        "": "3",
        "Severity": "3",
        "year": "2016",
        "lat": "39.747753",
        "lon": "-84.20558199999998",
        "Temperature": "35.1",
        "Pressure": "29.64",
        "Visibility": "9",
        "wheather": "Mostly Cloudy",
        "Day_night": "night",
        "WindSpeed": "3.5"
    },
    "4": {
        "": "4",
        "Severity": "2",
        "year": "2016",
        "lat": "39.627781",
        "lon": "-84.188354",
        "Temperature": "36.0",
        "Pressure": "29.65",
        "Visibility": "6",
        "wheather": "Mostly Cloudy",
        "Day_night": "day",
        "WindSpeed": "3.5"
    },
    "5": {
        "": "5",
        "Severity": "3",
        "year": "2016",
        "lat": "40.100590000000004",
        "lon": "-82.92519399999",
        "Temperature": "37.9",
        "Pressure": "29.63",
        "Visibility": "7",
        "wheather": "light rain",
        "Day_night": "day",
        "WindSpeed": "1.2"
    }
}